{
    "dontcare": [],
    "valid_line": [
        {
            "words": [
                {
                    "quad": {
                        "x2": 88,
                        "y3": 374,
                        "x3": 88,
                        "y4": 374,
                        "x1": 76,
                        "y1": 352,
                        "x4": 76,
                        "y2": 352
                    },
                    "is_key": 0,
                    "row_id": 2138651,
                    "text": "1"
                }
            ],
            "category": "menu.cnt",
            "group_id": 3
        },
        {
            "words": [
                {
                    "quad": {
                        "x2": 162,
                        "y3": 376,
                        "x3": 162,
                        "y4": 376,
                        "x1": 96,
                        "y1": 350,
                        "x4": 96,
                        "y2": 350
                    },
                    "is_key": 0,
                    "row_id": 2138651,
                    "text": "CHOCO"
                },
                {
                    "quad": {
                        "x2": 280,
                        "y3": 376,
                        "x3": 280,
                        "y4": 376,
                        "x1": 168,
                        "y1": 350,
                        "x4": 168,
                        "y2": 350
                    },
                    "is_key": 0,
                    "row_id": 2138651,
                    "text": "CROSSIANT"
                }
            ],
            "category": "menu.nm",
            "group_id": 3
        },
        {
            "words": [
                {
                    "quad": {
                        "x2": 512,
                        "y3": 380,
                        "x3": 512,
                        "y4": 380,
                        "x1": 434,
                        "y1": 352,
                        "x4": 434,
                        "y2": 352
                    },
                    "is_key": 0,
                    "row_id": 2138651,
                    "text": "13,000"
                }
            ],
            "category": "menu.price",
            "group_id": 3
        },
        {
            "words": [
                {
                    "quad": {
                        "x2": 218,
                        "y3": 454,
                        "x3": 218,
                        "y4": 454,
                        "x1": 98,
                        "y1": 408,
                        "x4": 98,
                        "y2": 408
                    },
                    "is_key": 1,
                    "row_id": 2138652,
                    "text": "TOTAL"
                },
                {
                    "quad": {
                        "x2": 510,
                        "y3": 460,
                        "x3": 510,
                        "y4": 460,
                        "x1": 364,
                        "y1": 412,
                        "x4": 364,
                        "y2": 412
                    },
                    "is_key": 0,
                    "row_id": 2138652,
                    "text": "13,000"
                }
            ],
            "category": "total.total_price",
            "group_id": 4
        },
        {
            "words": [
                {
                    "quad": {
                        "x2": 150,
                        "y3": 480,
                        "x3": 150,
                        "y4": 480,
                        "x1": 96,
                        "y1": 452,
                        "x4": 96,
                        "y2": 452
                    },
                    "is_key": 1,
                    "row_id": 2138653,
                    "text": "CASH"
                },
                {
                    "quad": {
                        "x2": 512,
                        "y3": 486,
                        "x3": 512,
                        "y4": 486,
                        "x1": 432,
                        "y1": 458,
                        "x4": 432,
                        "y2": 458
                    },
                    "is_key": 0,
                    "row_id": 2138653,
                    "text": "50,000"
                }
            ],
            "category": "total.cashprice",
            "group_id": 4
        },
        {
            "words": [
                {
                    "quad": {
                        "x2": 241,
                        "y3": 530,
                        "x3": 241,
                        "y4": 530,
                        "x1": 93,
                        "y1": 484,
                        "x4": 93,
                        "y2": 484
                    },
                    "is_key": 1,
                    "row_id": 2138654,
                    "text": "CHANGE"
                },
                {
                    "quad": {
                        "x2": 510,
                        "y3": 536,
                        "x3": 510,
                        "y4": 536,
                        "x1": 360,
                        "y1": 488,
                        "x4": 360,
                        "y2": 488
                    },
                    "is_key": 0,
                    "row_id": 2138654,
                    "text": "37,000"
                }
            ],
            "category": "total.changeprice",
            "group_id": 4
        }
    ],
    "meta": {
        "version": "v0.1",
        "split": "train",
        "image_id": 594,
        "image_size": {
            "width": 576,
            "height": 864
        }
    },
    "roi": {},
    "repeating_symbol": []
}